ipcmagic/__init__.py
ipcmagic/dask_cluster.py
ipcmagic/magics.py
ipcmagic/utilities.py
ipcmagic/version.py
ipcmagic_cscs-1.1.0.dist-info/METADATA
ipcmagic_cscs-1.1.0.dist-info/WHEEL
ipcmagic_cscs-1.1.0.dist-info/top_level.txt
ipcmagic_cscs-1.1.0.dist-info/RECORD
