Metadata-Version: 2.1
Name: ipcmagic-cscs
Version: 1.1.0
Summary: IPyParallel magics for Jupyter notebooks
Home-page: https://github.com/eth-cscs/ipcluster_magic
License: BSD 3-Clause
Requires-Dist: ipython (>=6.3.0)
Requires-Dist: docopt (>=0.6.2)
Requires-Dist: ipyparallel (>=8.2.1)
Provides-Extra: dask
Requires-Dist: dask[complete] (>=2022.05.0) ; extra == 'dask'
